LICENSE
MANIFEST.in
README.md
setup.py
inheritance/__init__.py
inheritance/__main__.py
inheritance/evalfam.py
inheritance/inheritance.py
inheritance/pyeval.py
inheritance.egg-info/PKG-INFO
inheritance.egg-info/SOURCES.txt
inheritance.egg-info/dependency_links.txt
inheritance.egg-info/not-zip-safe
inheritance.egg-info/top_level.txt
inheritance/tests/__init__.py
inheritance/tests/__init__.pyc
inheritance/tests/test_fuzz.py
inheritance/tests/test_fuzz.pyc
inheritance/tests/test_inheritance.py
inheritance/tests/test_inheritance.pyc