Metadata-Version: 1.1
Name: inheritance
Version: 0.0.5
Summary: inheritance models for mendelian genetics
Home-page: UNKNOWN
Author: Brent Pedersen
Author-email: bpederse@gmail.com
License: UNKNOWN
Platform: UNKNOWN
Classifier: Development Status :: 4 - Beta
Classifier: Intended Audience :: Science/Research
Classifier: License :: OSI Approved :: MIT License
Classifier: Topic :: Scientific/Engineering :: Bio-Informatics
